cytube_bot-0.2.1.dist-info/DESCRIPTION.rst
cytube_bot-0.2.1.dist-info/RECORD
cytube_bot-0.2.1.dist-info/WHEEL
cytube_bot-0.2.1.dist-info/top_level.txt
cytube_bot-0.2.1.dist-info/METADATA
cytube_bot-0.2.1.dist-info/metadata.json
cytube_bot/error.py
cytube_bot/__main__.py
cytube_bot/user.py
cytube_bot/__init__.py
cytube_bot/proxy.py
cytube_bot/util.py
cytube_bot/bot.py
cytube_bot/media_link.py
cytube_bot/playlist.py
cytube_bot/channel.py
cytube_bot/socket_io.py
