Metadata-Version: 2.0
Name: cytube-bot
Version: 0.2.1
Summary: AsyncIO CyTube bot
Home-page: https://github.com/dead-beef/cytube-bot
Author: dead-beef
Author-email: UNKNOWN
License: MIT
Keywords: cytube bot asyncio
Platform: UNKNOWN
Classifier: Development Status :: 4 - Beta
Classifier: Environment :: Web Environment
Classifier: Framework :: AsyncIO
Classifier: Intended Audience :: Developers
Classifier: License :: OSI Approved :: MIT License
Classifier: Programming Language :: Python :: 3
Classifier: Programming Language :: Python :: 3.4
Classifier: Topic :: Software Development :: Libraries :: Python Modules
Requires-Dist: websockets
Requires-Dist: requests
Provides-Extra: dev
Requires-Dist: pysocks; extra == 'dev'
Requires-Dist: pytest; extra == 'dev'
Requires-Dist: pytest-mock; extra == 'dev'
Requires-Dist: pytest-asyncio (<=0.5.0); extra == 'dev'
Requires-Dist: coverage; extra == 'dev'
Requires-Dist: sphinx; extra == 'dev'
Requires-Dist: sphinx-rtd-theme; extra == 'dev'
Requires-Dist: twine; extra == 'dev'
Requires-Dist: wheel; extra == 'dev'
Provides-Extra: proxy
Requires-Dist: pysocks; extra == 'proxy'
